sna4onnx/__init__.py
sna4onnx/__main__.py
sna4onnx/onnx_operation_adder.py
sna4onnx-1.0.6.dist-info/LICENSE
sna4onnx-1.0.6.dist-info/METADATA
sna4onnx-1.0.6.dist-info/WHEEL
sna4onnx-1.0.6.dist-info/entry_points.txt
sna4onnx-1.0.6.dist-info/top_level.txt
sna4onnx-1.0.6.dist-info/RECORD
