Metadata-Version: 2.1
Name: sna4onnx
Version: 1.0.6
Summary: Simple node addition tool for onnx. Simple Node Addition for ONNX.
Home-page: https://github.com/PINTO0309/sna4onnx
Author: Katsuya Hyodo
Author-email: rmsdh122@yahoo.co.jp
License: MIT License
Platform: linux
Platform: unix
Requires-Python: >=3.6
License-File: LICENSE
Requires-Dist: sog4onnx
